{
  "__inputs": [],
  "__requires": [
    {
      "type": "grafana",
      "id": "grafana",
      "name": "Grafana",
      "version": "9.0.0"
    },
    {
      "type": "datasource",
      "id": "cloudwatch",
      "name": "CloudWatch",
      "version": "1.0.0"
    }
  ],
  "annotations": {
    "list": []
  },
  "editable": true,
  "fiscalYearStartMonth": 0,
  "graphTooltip": 1,
  "id": null,
  "links": [],
  "panels": [
    {
      "collapsed": false,
      "gridPos": {
        "h": 1,
        "w": 24,
        "x": 0,
        "y": 0
      },
      "id": 100,
      "title": "EC2",
      "type": "row"
    },
    {
      "datasource": {
        "type": "cloudwatch",
        "uid": "cloudwatch-main"
      },
      "fieldConfig": {
        "defaults": {
          "color": {
            "mode": "palette-classic"
          },
          "custom": {
            "lineWidth": 2,
            "fillOpacity": 10
          },
          "unit": "percent",
          "min": 0,
          "max": 100,
          "links": [
            {
              "title": "Bedrock AI에게 질문",
              "url": "https://grafana.hyundong.shop/d/bedrock-qa/bedrock-qanda?orgId=1&from=now-6h&to=now&timezone=browser&var-q=EC2 인스턴스 ${instance_id}의 CPU 사용률이 ${__data.fields[0]} 시점에 ${__value.text}입니다. CloudWatch 메트릭: namespace=AWS/EC2, MetricName=CPUUtilization, InstanceId=${instance_id}. 이 수치가 정상인가요? 원인이 무엇일 수 있나요?",
              "targetBlank": true
            }
          ]
        }
      },
      "gridPos": {
        "h": 8,
        "w": 12,
        "x": 0,
        "y": 1
      },
      "id": 1,
      "options": {
        "tooltip": {
          "mode": "multi"
        }
      },
      "targets": [
        {
          "datasource": {
            "type": "cloudwatch",
            "uid": "cloudwatch-main"
          },
          "dimensions": {
            "InstanceId": "$instance_id"
          },
          "expression": "",
          "id": "",
          "matchExact": true,
          "metricEditorMode": 0,
          "metricName": "CPUUtilization",
          "metricQueryType": 0,
          "namespace": "AWS/EC2",
          "period": "$period",
          "queryMode": "Metrics",
          "refId": "A",
          "region": "default",
          "statistic": "Average"
        }
      ],
      "title": "EC2 CPU Utilization",
      "type": "timeseries",
      "links": [
        {
          "title": "이 차트에 대해 Bedrock AI에게 질문",
          "url": "https://grafana.hyundong.shop/d/bedrock-qa/bedrock-qanda?orgId=1&from=${__from}&to=${__to}&timezone=browser&var-q=EC2 인스턴스 ${instance_id}의 CPU 사용률 추이를 분석해 주세요. CloudWatch 메트릭: namespace=AWS/EC2, MetricName=CPUUtilization, InstanceId=${instance_id}. 패턴이 정상인가요? 급등하거나 지속적으로 높은 사용률이 있나요?",
          "targetBlank": true
        }
      ]
    },
    {
      "datasource": {
        "type": "cloudwatch",
        "uid": "cloudwatch-main"
      },
      "fieldConfig": {
        "defaults": {
          "color": {
            "mode": "palette-classic"
          },
          "custom": {
            "lineWidth": 2,
            "fillOpacity": 10
          },
          "unit": "bytes",
          "min": 0,
          "links": [
            {
              "title": "Bedrock AI에게 질문",
              "url": "https://grafana.hyundong.shop/d/bedrock-qa/bedrock-qanda?orgId=1&from=now-6h&to=now&timezone=browser&var-q=EC2 인스턴스 ${instance_id}의 ${__data.fields[0]} 시점 ${__series.name}이 ${__value.text}입니다. CloudWatch 메트릭: namespace=AWS/EC2, MetricName=NetworkIn 및 NetworkOut, InstanceId=${instance_id}. 이 트래픽 수준이 정상인가요?",
              "targetBlank": true
            }
          ]
        }
      },
      "gridPos": {
        "h": 8,
        "w": 12,
        "x": 12,
        "y": 1
      },
      "id": 2,
      "targets": [
        {
          "datasource": {
            "type": "cloudwatch",
            "uid": "cloudwatch-main"
          },
          "dimensions": {
            "InstanceId": "$instance_id"
          },
          "metricName": "NetworkIn",
          "namespace": "AWS/EC2",
          "period": "$period",
          "queryMode": "Metrics",
          "refId": "A",
          "region": "default",
          "statistic": "Sum",
          "expression": "",
          "id": "",
          "matchExact": true,
          "metricEditorMode": 0,
          "metricQueryType": 0
        },
        {
          "datasource": {
            "type": "cloudwatch",
            "uid": "cloudwatch-main"
          },
          "dimensions": {
            "InstanceId": "$instance_id"
          },
          "metricName": "NetworkOut",
          "namespace": "AWS/EC2",
          "period": "$period",
          "queryMode": "Metrics",
          "refId": "B",
          "region": "default",
          "statistic": "Sum",
          "expression": "",
          "id": "",
          "matchExact": true,
          "metricEditorMode": 0,
          "metricQueryType": 0
        }
      ],
      "title": "EC2 Network In / Out",
      "type": "timeseries",
      "links": [
        {
          "title": "이 차트에 대해 Bedrock AI에게 질문",
          "url": "https://grafana.hyundong.shop/d/bedrock-qa/bedrock-qanda?orgId=1&from=${__from}&to=${__to}&timezone=browser&var-q=EC2 인스턴스 ${instance_id}의 네트워크 트래픽(수신/송신)을 분석해 주세요. CloudWatch 메트릭: namespace=AWS/EC2, MetricName=NetworkIn 및 NetworkOut, InstanceId=${instance_id}. 이상 징후나 예상치 못한 트래픽 패턴이 있나요?",
          "targetBlank": true
        }
      ]
    },
    {
      "datasource": {
        "type": "cloudwatch",
        "uid": "cloudwatch-main"
      },
      "fieldConfig": {
        "defaults": {
          "color": {
            "mode": "palette-classic"
          },
          "custom": {
            "lineWidth": 2,
            "fillOpacity": 10
          },
          "unit": "iops",
          "min": 0,
          "links": [
            {
              "title": "Bedrock AI에게 질문",
              "url": "https://grafana.hyundong.shop/d/bedrock-qa/bedrock-qanda?orgId=1&from=now-6h&to=now&timezone=browser&var-q=EC2 인스턴스 ${instance_id}의 ${__data.fields[0]} 시점 ${__series.name}이 ${__value.text}입니다. CloudWatch 메트릭: namespace=AWS/EC2, MetricName=DiskReadOps 및 DiskWriteOps, InstanceId=${instance_id}. 이 디스크 I/O가 정상인가요?",
              "targetBlank": true
            }
          ]
        }
      },
      "gridPos": {
        "h": 8,
        "w": 12,
        "x": 0,
        "y": 9
      },
      "id": 3,
      "targets": [
        {
          "datasource": {
            "type": "cloudwatch",
            "uid": "cloudwatch-main"
          },
          "dimensions": {
            "InstanceId": "$instance_id"
          },
          "metricName": "DiskReadOps",
          "namespace": "AWS/EC2",
          "period": "$period",
          "queryMode": "Metrics",
          "refId": "A",
          "region": "default",
          "statistic": "Sum",
          "expression": "",
          "id": "",
          "matchExact": true,
          "metricEditorMode": 0,
          "metricQueryType": 0
        },
        {
          "datasource": {
            "type": "cloudwatch",
            "uid": "cloudwatch-main"
          },
          "dimensions": {
            "InstanceId": "$instance_id"
          },
          "metricName": "DiskWriteOps",
          "namespace": "AWS/EC2",
          "period": "$period",
          "queryMode": "Metrics",
          "refId": "B",
          "region": "default",
          "statistic": "Sum",
          "expression": "",
          "id": "",
          "matchExact": true,
          "metricEditorMode": 0,
          "metricQueryType": 0
        }
      ],
      "title": "EC2 Disk Read / Write IOPS",
      "type": "timeseries",
      "links": [
        {
          "title": "이 차트에 대해 Bedrock AI에게 질문",
          "url": "https://grafana.hyundong.shop/d/bedrock-qa/bedrock-qanda?orgId=1&from=${__from}&to=${__to}&timezone=browser&var-q=EC2 인스턴스 ${instance_id}의 디스크 읽기/쓰기 IOPS를 분석해 주세요. CloudWatch 메트릭: namespace=AWS/EC2, MetricName=DiskReadOps 및 DiskWriteOps, InstanceId=${instance_id}. 이 I/O 패턴이 워크로드에 적합한가요?",
          "targetBlank": true
        }
      ]
    },
    {
      "datasource": {
        "type": "cloudwatch",
        "uid": "cloudwatch-main"
      },
      "fieldConfig": {
        "defaults": {
          "color": {
            "mode": "thresholds"
          },
          "thresholds": {
            "mode": "absolute",
            "steps": [
              {
                "color": "green",
                "value": null
              },
              {
                "color": "yellow",
                "value": 60
              },
              {
                "color": "red",
                "value": 85
              }
            ]
          },
          "unit": "percent",
          "min": 0,
          "max": 100,
          "mappings": [],
          "links": [
            {
              "title": "Bedrock AI에게 질문",
              "url": "https://grafana.hyundong.shop/d/bedrock-qa/bedrock-qanda?orgId=1&from=now-6h&to=now&timezone=browser&var-q=EC2 인스턴스 ${instance_id}의 현재 CPU 사용률이 ${__value.text}입니다. CloudWatch 메트릭: namespace=AWS/EC2, MetricName=CPUUtilization, InstanceId=${instance_id}. 우려할 수준인가요? 어떻게 조치하면 좋을까요?",
              "targetBlank": true
            }
          ]
        }
      },
      "gridPos": {
        "h": 8,
        "w": 12,
        "x": 12,
        "y": 9
      },
      "id": 4,
      "options": {
        "reduceOptions": {
          "calcs": [
            "lastNotNull"
          ]
        },
        "orientation": "auto",
        "textMode": "auto",
        "colorMode": "background"
      },
      "targets": [
        {
          "datasource": {
            "type": "cloudwatch",
            "uid": "cloudwatch-main"
          },
          "dimensions": {
            "InstanceId": "$instance_id"
          },
          "metricName": "CPUUtilization",
          "namespace": "AWS/EC2",
          "period": "300",
          "queryMode": "Metrics",
          "refId": "A",
          "region": "default",
          "statistic": "Average",
          "expression": "",
          "id": "",
          "matchExact": true,
          "metricEditorMode": 0,
          "metricQueryType": 0
        }
      ],
      "title": "EC2 CPU (current)",
      "type": "stat",
      "links": [
        {
          "title": "이 차트에 대해 Bedrock AI에게 질문",
          "url": "https://grafana.hyundong.shop/d/bedrock-qa/bedrock-qanda?orgId=1&from=${__from}&to=${__to}&timezone=browser&var-q=EC2 인스턴스 ${instance_id}의 현재 CPU 사용률은 얼마인가요? CloudWatch 메트릭: namespace=AWS/EC2, MetricName=CPUUtilization, InstanceId=${instance_id}. 이 수준이 우려스러운가요?",
          "targetBlank": true
        }
      ]
    },
    {
      "collapsed": false,
      "gridPos": {
        "h": 1,
        "w": 24,
        "x": 0,
        "y": 17
      },
      "id": 101,
      "title": "Lambda \u2014 bedrock-qa",
      "type": "row"
    },
    {
      "datasource": {
        "type": "cloudwatch",
        "uid": "cloudwatch-main"
      },
      "fieldConfig": {
        "defaults": {
          "color": {
            "mode": "palette-classic"
          },
          "custom": {
            "lineWidth": 2,
            "fillOpacity": 10
          },
          "unit": "short",
          "min": 0,
          "links": [
            {
              "title": "Bedrock AI에게 질문",
              "url": "https://grafana.hyundong.shop/d/bedrock-qa/bedrock-qanda?orgId=1&from=now-6h&to=now&timezone=browser&var-q=Lambda 함수 bedrock-qa가 ${__data.fields[0]} 시점에 ${__value.text}번 호출되었습니다. CloudWatch 메트릭: namespace=AWS/Lambda, MetricName=Invocations, FunctionName=bedrock-qa. 이 트래픽 수준이 정상인가요?",
              "targetBlank": true
            }
          ]
        }
      },
      "gridPos": {
        "h": 8,
        "w": 12,
        "x": 0,
        "y": 18
      },
      "id": 5,
      "targets": [
        {
          "datasource": {
            "type": "cloudwatch",
            "uid": "cloudwatch-main"
          },
          "dimensions": {
            "FunctionName": "bedrock-qa"
          },
          "metricName": "Invocations",
          "namespace": "AWS/Lambda",
          "period": "$period",
          "queryMode": "Metrics",
          "refId": "A",
          "region": "default",
          "statistic": "Sum",
          "expression": "",
          "id": "",
          "matchExact": true,
          "metricEditorMode": 0,
          "metricQueryType": 0
        }
      ],
      "title": "Lambda Invocations",
      "type": "timeseries",
      "links": [
        {
          "title": "이 차트에 대해 Bedrock AI에게 질문",
          "url": "https://grafana.hyundong.shop/d/bedrock-qa/bedrock-qanda?orgId=1&from=${__from}&to=${__to}&timezone=browser&var-q=Lambda 함수 bedrock-qa의 호출 추이를 분석해 주세요. CloudWatch 메트릭: namespace=AWS/Lambda, MetricName=Invocations, FunctionName=bedrock-qa. 호출 횟수에 이상한 급등이나 감소가 있나요?",
          "targetBlank": true
        }
      ]
    },
    {
      "datasource": {
        "type": "cloudwatch",
        "uid": "cloudwatch-main"
      },
      "fieldConfig": {
        "defaults": {
          "color": {
            "mode": "palette-classic"
          },
          "custom": {
            "lineWidth": 2,
            "fillOpacity": 10
          },
          "unit": "ms",
          "min": 0,
          "links": [
            {
              "title": "Bedrock AI에게 질문",
              "url": "https://grafana.hyundong.shop/d/bedrock-qa/bedrock-qanda?orgId=1&from=now-6h&to=now&timezone=browser&var-q=Lambda 함수 bedrock-qa의 ${__data.fields[0]} 시점 ${__series.name} 실행 시간이 ${__value.text}입니다. CloudWatch 메트릭: namespace=AWS/Lambda, MetricName=Duration, FunctionName=bedrock-qa. 이 성능이 적절한가요?",
              "targetBlank": true
            }
          ]
        }
      },
      "gridPos": {
        "h": 8,
        "w": 12,
        "x": 12,
        "y": 18
      },
      "id": 6,
      "targets": [
        {
          "datasource": {
            "type": "cloudwatch",
            "uid": "cloudwatch-main"
          },
          "dimensions": {
            "FunctionName": "bedrock-qa"
          },
          "metricName": "Duration",
          "namespace": "AWS/Lambda",
          "period": "$period",
          "queryMode": "Metrics",
          "refId": "A",
          "region": "default",
          "statistic": "Average",
          "expression": "",
          "id": "",
          "matchExact": true,
          "metricEditorMode": 0,
          "metricQueryType": 0
        },
        {
          "datasource": {
            "type": "cloudwatch",
            "uid": "cloudwatch-main"
          },
          "dimensions": {
            "FunctionName": "bedrock-qa"
          },
          "metricName": "Duration",
          "namespace": "AWS/Lambda",
          "period": "$period",
          "queryMode": "Metrics",
          "refId": "B",
          "region": "default",
          "statistic": "p95",
          "expression": "",
          "id": "",
          "matchExact": true,
          "metricEditorMode": 0,
          "metricQueryType": 0
        }
      ],
      "title": "Lambda Duration (avg / p95)",
      "type": "timeseries",
      "links": [
        {
          "title": "이 차트에 대해 Bedrock AI에게 질문",
          "url": "https://grafana.hyundong.shop/d/bedrock-qa/bedrock-qanda?orgId=1&from=${__from}&to=${__to}&timezone=browser&var-q=Lambda 함수 bedrock-qa의 실행 시간(평균 및 p95)을 분석해 주세요. CloudWatch 메트릭: namespace=AWS/Lambda, MetricName=Duration, FunctionName=bedrock-qa. 성능이 정상인가요? 레이턴시 증가가 있나요?",
          "targetBlank": true
        }
      ]
    },
    {
      "datasource": {
        "type": "cloudwatch",
        "uid": "cloudwatch-main"
      },
      "fieldConfig": {
        "defaults": {
          "color": {
            "mode": "palette-classic"
          },
          "custom": {
            "lineWidth": 2,
            "fillOpacity": 20
          },
          "unit": "short",
          "min": 0,
          "links": [
            {
              "title": "Bedrock AI에게 질문",
              "url": "https://grafana.hyundong.shop/d/bedrock-qa/bedrock-qanda?orgId=1&from=now-6h&to=now&timezone=browser&var-q=Lambda 함수 bedrock-qa에서 ${__data.fields[0]} 시점에 ${__series.name} ${__value.text}이 발생했습니다. CloudWatch 메트릭: namespace=AWS/Lambda, MetricName=Errors 및 Throttles, FunctionName=bedrock-qa. 원인이 무엇이며 어떻게 조사해야 하나요?",
              "targetBlank": true
            }
          ]
        },
        "overrides": [
          {
            "matcher": {
              "id": "byName",
              "options": "Errors"
            },
            "properties": [
              {
                "id": "color",
                "value": {
                  "fixedColor": "red",
                  "mode": "fixed"
                }
              }
            ]
          },
          {
            "matcher": {
              "id": "byName",
              "options": "Throttles"
            },
            "properties": [
              {
                "id": "color",
                "value": {
                  "fixedColor": "orange",
                  "mode": "fixed"
                }
              }
            ]
          }
        ]
      },
      "gridPos": {
        "h": 8,
        "w": 12,
        "x": 0,
        "y": 26
      },
      "id": 7,
      "targets": [
        {
          "datasource": {
            "type": "cloudwatch",
            "uid": "cloudwatch-main"
          },
          "dimensions": {
            "FunctionName": "bedrock-qa"
          },
          "metricName": "Errors",
          "namespace": "AWS/Lambda",
          "period": "$period",
          "queryMode": "Metrics",
          "refId": "A",
          "region": "default",
          "statistic": "Sum",
          "expression": "",
          "id": "",
          "matchExact": true,
          "metricEditorMode": 0,
          "metricQueryType": 0
        },
        {
          "datasource": {
            "type": "cloudwatch",
            "uid": "cloudwatch-main"
          },
          "dimensions": {
            "FunctionName": "bedrock-qa"
          },
          "metricName": "Throttles",
          "namespace": "AWS/Lambda",
          "period": "$period",
          "queryMode": "Metrics",
          "refId": "B",
          "region": "default",
          "statistic": "Sum",
          "expression": "",
          "id": "",
          "matchExact": true,
          "metricEditorMode": 0,
          "metricQueryType": 0
        }
      ],
      "title": "Lambda Errors / Throttles",
      "type": "timeseries",
      "links": [
        {
          "title": "이 차트에 대해 Bedrock AI에게 질문",
          "url": "https://grafana.hyundong.shop/d/bedrock-qa/bedrock-qanda?orgId=1&from=${__from}&to=${__to}&timezone=browser&var-q=Lambda 함수 bedrock-qa의 오류 및 스로틀링을 분석해 주세요. CloudWatch 메트릭: namespace=AWS/Lambda, MetricName=Errors 및 Throttles, FunctionName=bedrock-qa. 원인이 무엇이며 어떻게 해결해야 하나요?",
          "targetBlank": true
        }
      ]
    },
    {
      "datasource": {
        "type": "cloudwatch",
        "uid": "cloudwatch-main"
      },
      "fieldConfig": {
        "defaults": {
          "color": {
            "mode": "palette-classic"
          },
          "custom": {
            "lineWidth": 2,
            "fillOpacity": 10
          },
          "unit": "short",
          "min": 0,
          "links": [
            {
              "title": "Bedrock AI에게 질문",
              "url": "https://grafana.hyundong.shop/d/bedrock-qa/bedrock-qanda?orgId=1&from=now-6h&to=now&timezone=browser&var-q=Lambda 함수 bedrock-qa가 ${__data.fields[0]} 시점에 동시 실행 수 ${__value.text}를 기록했습니다. CloudWatch 메트릭: namespace=AWS/Lambda, MetricName=ConcurrentExecutions, FunctionName=bedrock-qa. 동시 실행 한도를 주의해야 하나요?",
              "targetBlank": true
            }
          ]
        }
      },
      "gridPos": {
        "h": 8,
        "w": 12,
        "x": 12,
        "y": 26
      },
      "id": 8,
      "targets": [
        {
          "datasource": {
            "type": "cloudwatch",
            "uid": "cloudwatch-main"
          },
          "dimensions": {
            "FunctionName": "bedrock-qa"
          },
          "metricName": "ConcurrentExecutions",
          "namespace": "AWS/Lambda",
          "period": "$period",
          "queryMode": "Metrics",
          "refId": "A",
          "region": "default",
          "statistic": "Maximum",
          "expression": "",
          "id": "",
          "matchExact": true,
          "metricEditorMode": 0,
          "metricQueryType": 0
        }
      ],
      "title": "Lambda Concurrent Executions",
      "type": "timeseries",
      "links": [
        {
          "title": "이 차트에 대해 Bedrock AI에게 질문",
          "url": "https://grafana.hyundong.shop/d/bedrock-qa/bedrock-qanda?orgId=1&from=${__from}&to=${__to}&timezone=browser&var-q=Lambda 함수 bedrock-qa의 동시 실행 수 추이를 분석해 주세요. CloudWatch 메트릭: namespace=AWS/Lambda, MetricName=ConcurrentExecutions, FunctionName=bedrock-qa. 동시 실행 한도에 근접하고 있나요?",
          "targetBlank": true
        }
      ]
    },
    {
      "collapsed": false,
      "gridPos": {
        "h": 1,
        "w": 24,
        "x": 0,
        "y": 34
      },
      "id": 102,
      "title": "EC2 \u2014 Memory & Disk (CloudWatch Agent)",
      "type": "row"
    },
    {
      "datasource": {
        "type": "cloudwatch",
        "uid": "cloudwatch-main"
      },
      "fieldConfig": {
        "defaults": {
          "color": {
            "mode": "palette-classic"
          },
          "custom": {
            "lineWidth": 2,
            "fillOpacity": 15
          },
          "unit": "percent",
          "min": 0,
          "max": 100,
          "thresholds": {
            "mode": "absolute",
            "steps": [
              {
                "color": "green",
                "value": null
              },
              {
                "color": "yellow",
                "value": 70
              },
              {
                "color": "red",
                "value": 85
              }
            ]
          },
          "links": [
            {
              "title": "Bedrock AI에게 질문",
              "url": "https://grafana.hyundong.shop/d/bedrock-qa/bedrock-qanda?orgId=1&from=now-6h&to=now&timezone=browser&var-q=EC2 인스턴스 ${instance_id}의 ${__data.fields[0]} 시점 메모리 사용률이 ${__value.text}입니다. CloudWatch 메트릭: namespace=CWAgent, MetricName=mem_used_percent, InstanceId=${instance_id}. 우려스러운 수준인가요? 무엇이 메모리를 소비하고 있을까요?",
              "targetBlank": true
            }
          ]
        }
      },
      "gridPos": {
        "h": 8,
        "w": 12,
        "x": 0,
        "y": 35
      },
      "id": 10,
      "targets": [
        {
          "datasource": {
            "type": "cloudwatch",
            "uid": "cloudwatch-main"
          },
          "dimensions": {
            "InstanceId": "$instance_id"
          },
          "expression": "",
          "id": "",
          "matchExact": true,
          "metricEditorMode": 0,
          "metricQueryType": 0,
          "metricName": "mem_used_percent",
          "namespace": "CWAgent",
          "period": "$period",
          "queryMode": "Metrics",
          "refId": "A",
          "region": "default",
          "statistic": "Average"
        }
      ],
      "title": "EC2 Memory Usage",
      "type": "timeseries",
      "links": [
        {
          "title": "이 차트에 대해 Bedrock AI에게 질문",
          "url": "https://grafana.hyundong.shop/d/bedrock-qa/bedrock-qanda?orgId=1&from=${__from}&to=${__to}&timezone=browser&var-q=EC2 인스턴스 ${instance_id}의 메모리 사용률을 분석해 주세요. CloudWatch 메트릭: namespace=CWAgent, MetricName=mem_used_percent, InstanceId=${instance_id}. 메모리 압박이나 누수 가능성이 있나요?",
          "targetBlank": true
        }
      ]
    },
    {
      "datasource": {
        "type": "cloudwatch",
        "uid": "cloudwatch-main"
      },
      "fieldConfig": {
        "defaults": {
          "color": {
            "mode": "palette-classic"
          },
          "custom": {
            "lineWidth": 2,
            "fillOpacity": 15
          },
          "unit": "percent",
          "min": 0,
          "max": 100,
          "thresholds": {
            "mode": "absolute",
            "steps": [
              {
                "color": "green",
                "value": null
              },
              {
                "color": "yellow",
                "value": 75
              },
              {
                "color": "red",
                "value": 90
              }
            ]
          },
          "links": [
            {
              "title": "Bedrock AI에게 질문",
              "url": "https://grafana.hyundong.shop/d/bedrock-qa/bedrock-qanda?orgId=1&from=now-6h&to=now&timezone=browser&var-q=EC2 인스턴스 ${instance_id}의 ${__data.fields[0]} 시점 루트(/) 디스크 사용률이 ${__value.text}입니다. CloudWatch 메트릭: namespace=CWAgent, MetricName=disk_used_percent, path=/, InstanceId=${instance_id}. 우려할 수준인가요? 무엇을 정리해야 할까요?",
              "targetBlank": true
            }
          ]
        }
      },
      "gridPos": {
        "h": 8,
        "w": 12,
        "x": 12,
        "y": 35
      },
      "id": 11,
      "targets": [
        {
          "datasource": {
            "type": "cloudwatch",
            "uid": "cloudwatch-main"
          },
          "dimensions": {
            "InstanceId": "$instance_id",
            "path": "/",
            "device": "nvme0n1p1",
            "fstype": "xfs"
          },
          "expression": "",
          "id": "",
          "matchExact": false,
          "metricEditorMode": 0,
          "metricQueryType": 0,
          "metricName": "disk_used_percent",
          "namespace": "CWAgent",
          "period": "$period",
          "queryMode": "Metrics",
          "refId": "A",
          "region": "default",
          "statistic": "Average"
        }
      ],
      "title": "EC2 Disk Usage (/)",
      "type": "timeseries",
      "links": [
        {
          "title": "이 차트에 대해 Bedrock AI에게 질문",
          "url": "https://grafana.hyundong.shop/d/bedrock-qa/bedrock-qanda?orgId=1&from=${__from}&to=${__to}&timezone=browser&var-q=EC2 인스턴스 ${instance_id}의 루트(/) 디스크 사용률을 분석해 주세요. CloudWatch 메트릭: namespace=CWAgent, MetricName=disk_used_percent, path=/, InstanceId=${instance_id}. 곧 디스크 공간이 부족해질 위험이 있나요?",
          "targetBlank": true
        }
      ]
    },
    {
      "datasource": {
        "type": "cloudwatch",
        "uid": "cloudwatch-main"
      },
      "fieldConfig": {
        "defaults": {
          "color": {
            "mode": "thresholds"
          },
          "thresholds": {
            "mode": "absolute",
            "steps": [
              {
                "color": "green",
                "value": null
              },
              {
                "color": "yellow",
                "value": 70
              },
              {
                "color": "red",
                "value": 85
              }
            ]
          },
          "unit": "percent",
          "min": 0,
          "max": 100,
          "mappings": []
        }
      },
      "gridPos": {
        "h": 4,
        "w": 6,
        "x": 0,
        "y": 43
      },
      "id": 12,
      "options": {
        "reduceOptions": {
          "calcs": [
            "lastNotNull"
          ]
        },
        "orientation": "auto",
        "textMode": "auto",
        "colorMode": "background"
      },
      "targets": [
        {
          "datasource": {
            "type": "cloudwatch",
            "uid": "cloudwatch-main"
          },
          "dimensions": {
            "InstanceId": "$instance_id"
          },
          "expression": "",
          "id": "",
          "matchExact": true,
          "metricEditorMode": 0,
          "metricQueryType": 0,
          "metricName": "mem_used_percent",
          "namespace": "CWAgent",
          "period": "300",
          "queryMode": "Metrics",
          "refId": "A",
          "region": "default",
          "statistic": "Average"
        }
      ],
      "title": "Memory (current)",
      "type": "stat",
      "links": [
        {
          "title": "이 차트에 대해 Bedrock AI에게 질문",
          "url": "https://grafana.hyundong.shop/d/bedrock-qa/bedrock-qanda?orgId=1&from=${__from}&to=${__to}&timezone=browser&var-q=EC2 인스턴스 ${instance_id}의 현재 메모리 사용률은 얼마인가요? CloudWatch 메트릭: namespace=CWAgent, MetricName=mem_used_percent, InstanceId=${instance_id}. 이 수준이 우려스러운가요?",
          "targetBlank": true
        }
      ]
    },
    {
      "datasource": {
        "type": "cloudwatch",
        "uid": "cloudwatch-main"
      },
      "fieldConfig": {
        "defaults": {
          "color": {
            "mode": "thresholds"
          },
          "thresholds": {
            "mode": "absolute",
            "steps": [
              {
                "color": "green",
                "value": null
              },
              {
                "color": "yellow",
                "value": 75
              },
              {
                "color": "red",
                "value": 90
              }
            ]
          },
          "unit": "percent",
          "min": 0,
          "max": 100,
          "mappings": []
        }
      },
      "gridPos": {
        "h": 4,
        "w": 6,
        "x": 6,
        "y": 43
      },
      "id": 13,
      "options": {
        "reduceOptions": {
          "calcs": [
            "lastNotNull"
          ]
        },
        "orientation": "auto",
        "textMode": "auto",
        "colorMode": "background"
      },
      "targets": [
        {
          "datasource": {
            "type": "cloudwatch",
            "uid": "cloudwatch-main"
          },
          "dimensions": {
            "InstanceId": "$instance_id",
            "path": "/",
            "device": "nvme0n1p1",
            "fstype": "xfs"
          },
          "expression": "",
          "id": "",
          "matchExact": false,
          "metricEditorMode": 0,
          "metricQueryType": 0,
          "metricName": "disk_used_percent",
          "namespace": "CWAgent",
          "period": "300",
          "queryMode": "Metrics",
          "refId": "A",
          "region": "default",
          "statistic": "Average"
        }
      ],
      "title": "Disk Usage / (current)",
      "type": "stat",
      "links": [
        {
          "title": "이 차트에 대해 Bedrock AI에게 질문",
          "url": "https://grafana.hyundong.shop/d/bedrock-qa/bedrock-qanda?orgId=1&from=${__from}&to=${__to}&timezone=browser&var-q=EC2 인스턴스 ${instance_id}의 현재 루트(/) 디스크 사용률은 얼마인가요? CloudWatch 메트릭: namespace=CWAgent, MetricName=disk_used_percent, path=/, InstanceId=${instance_id}. 디스크 공간이 부족해지고 있나요?",
          "targetBlank": true
        }
      ]
    }
  ],
  "refresh": "30s",
  "schemaVersion": 38,
  "tags": [
    "aws",
    "cloudwatch",
    "ec2",
    "lambda"
  ],
  "templating": {
    "list": [
      {
        "current": {},
        "datasource": {
          "type": "cloudwatch",
          "uid": "cloudwatch-main"
        },
        "definition": "dimension_values(default,AWS/EC2,CPUUtilization,InstanceId)",
        "hide": 0,
        "includeAll": false,
        "name": "instance_id",
        "options": [],
        "query": "dimension_values(default,AWS/EC2,CPUUtilization,InstanceId)",
        "refresh": 2,
        "type": "query",
        "label": "EC2 Instance"
      },
      {
        "current": {
          "selected": false,
          "text": "300",
          "value": "300"
        },
        "hide": 0,
        "includeAll": false,
        "name": "period",
        "options": [
          {
            "selected": false,
            "text": "1m",
            "value": "60"
          },
          {
            "selected": true,
            "text": "5m",
            "value": "300"
          },
          {
            "selected": false,
            "text": "15m",
            "value": "900"
          },
          {
            "selected": false,
            "text": "1h",
            "value": "3600"
          }
        ],
        "query": "60,300,900,3600",
        "type": "custom",
        "label": "Period"
      }
    ]
  },
  "time": {
    "from": "now-3h",
    "to": "now"
  },
  "timepicker": {},
  "timezone": "browser",
  "title": "AWS CloudWatch \u2014 EC2 & Lambda",
  "uid": "aws-cloudwatch-main",
  "version": 2
}